ncompass.pth
ncompass_init.py
ncompass/__init__.py
ncompass/py.typed
ncompass/bin/nsys-chrome
ncompass/cli/__init__.py
ncompass/cli/__main__.py
ncompass/cli/convert.py
ncompass/cli/main.py
ncompass/cli/profile.py
ncompass/profile/__init__.py
ncompass/profile/nsys.py
ncompass/trace/__init__.py
ncompass/trace/converters/__init__.py
ncompass/trace/converters/converter.py
ncompass/trace/converters/mapping.py
ncompass/trace/converters/models.py
ncompass/trace/converters/schema.py
ncompass/trace/converters/utils.py
ncompass/trace/converters/linker/__init__.py
ncompass/trace/converters/linker/adapters.py
ncompass/trace/converters/linker/algorithms.py
ncompass/trace/converters/linker/nvtx_linker.py
ncompass/trace/converters/linker/user_annotation_linker.py
ncompass/trace/converters/parsers/__init__.py
ncompass/trace/converters/parsers/base.py
ncompass/trace/converters/parsers/composite.py
ncompass/trace/converters/parsers/cupti.py
ncompass/trace/converters/parsers/default.py
ncompass/trace/converters/parsers/nvtx.py
ncompass/trace/converters/parsers/osrt.py
ncompass/trace/converters/parsers/sched.py
ncompass/trace/core/__init__.py
ncompass/trace/core/config_manager.py
ncompass/trace/core/finder.py
ncompass/trace/core/loader.py
ncompass/trace/core/pydantic.py
ncompass/trace/core/rewrite.py
ncompass/trace/core/session.py
ncompass/trace/core/utils.py
ncompass/trace/infra/__init__.py
ncompass/trace/infra/utils.py
ncompass/trace/profile/__init__.py
ncompass/trace/profile/base.py
ncompass/trace/profile/nvtx.py
ncompass/trace/profile/torch.py
ncompass/trace/replacers/__init__.py
ncompass/trace/replacers/base.py
ncompass/trace/replacers/dynamic.py
ncompass/trace/replacers/utils.py
ncompass/types/__init__.py
ncompass/types/immutable.py
ncompass/types/ncbase.py
ncompass/types/trait.py
ncompass-0.1.12.data/data/ncompass.pth
ncompass-0.1.12.data/data/ncompass_init.py
ncompass-0.1.12.dist-info/licenses/LICENSE
ncompass-0.1.12.dist-info/METADATA
ncompass-0.1.12.dist-info/WHEEL
ncompass-0.1.12.dist-info/entry_points.txt
ncompass-0.1.12.dist-info/top_level.txt
ncompass-0.1.12.dist-info/RECORD
