Metadata-Version: 2.4
Name: ncompass
Version: 0.1.12
Summary: Profiling and trace analysis SDK
Author-email: nCompass Technologies <support@ncompass.tech>
Maintainer-email: nCompass Technologies <support@ncompass.tech>
License: Apache-2.0
Project-URL: Homepage, https://ncompass.tech
Project-URL: Documentation, https://docs.ncompass.tech
Project-URL: Repository, https://github.com/ncompass-tech/ncompass
Project-URL: Community, https://community.ncompass.tech
Project-URL: Bug Tracker, https://github.com/ncompass-tech/ncompass/issues
Keywords: ai,inference,profiling,tracing,performance,gpu,pytorch,cuda
Classifier: Development Status :: 3 - Alpha
Classifier: Intended Audience :: Developers
Classifier: Intended Audience :: Science/Research
Classifier: License :: OSI Approved :: Apache Software License
Classifier: Operating System :: OS Independent
Classifier: Programming Language :: Python :: 3
Classifier: Programming Language :: Python :: 3.10
Classifier: Programming Language :: Python :: 3.11
Classifier: Programming Language :: Python :: 3.12
Classifier: Topic :: Scientific/Engineering :: Artificial Intelligence
Classifier: Topic :: Software Development :: Libraries :: Python Modules
Requires-Python: >=3.10
License-File: LICENSE
Requires-Dist: requests>=2.28.0
Requires-Dist: pydantic>2.0.0
Requires-Dist: orjson>=3.9.0
Requires-Dist: tomli>=2.0.0; python_version < "3.11"
Requires-Dist: typing_extensions>=4.0.0; python_version < "3.11"
Provides-Extra: dev
Requires-Dist: pytest>=7.0.0; extra == "dev"
Requires-Dist: pytest-cov>=4.0.0; extra == "dev"
Requires-Dist: interrogate>=1.5.0; extra == "dev"
Requires-Dist: pyright>=1.1.0; extra == "dev"
Requires-Dist: mypy>=1.0.0; extra == "dev"
Requires-Dist: black>=23.0.0; extra == "dev"
Requires-Dist: isort>=5.12.0; extra == "dev"
Requires-Dist: ruff>=0.1.0; extra == "dev"
Requires-Dist: pyyaml>=6.0; extra == "dev"
Provides-Extra: docs
Requires-Dist: sphinx>=5.0.0; extra == "docs"
Requires-Dist: sphinx-rtd-theme>=1.2.0; extra == "docs"
Requires-Dist: myst-parser>=1.0.0; extra == "docs"
Dynamic: license-file
